<?xml version = '1.0' encoding = 'UTF-8'?>
<SegmentOraclev10g class="oracle.dbtools.crest.model.design.storage.oracle.v10g.SegmentOraclev10g" name="Storage4" directorySegmentName="seg_0" id="2F029F5F-9AA4-635A-6833-C939E5A3980B">
<createdBy>Ulises III</createdBy>
<createdTime>2025-11-05 22:50:31 UTC</createdTime>
<ownerDesignName>anotacionesdb</ownerDesignName>
<initrans>2</initrans>
<maxTrans>255</maxTrans>
<scInitialExtent>65536</scInitialExtent>
<scMaxExtents>2147483645</scMaxExtents>
<scNextExtent>1048576</scNextExtent>
</SegmentOraclev10g>